clag/__init__.py
clag/cli.py
clag/error_handling.py
clag/generator.py
clag/listener.py
clag/models.py
clag/parser.py
clag/antlr/ClagLexer.g4
clag/antlr/ClagLexer.interp
clag/antlr/ClagLexer.py
clag/antlr/ClagLexer.tokens
clag/antlr/ClagParser.g4
clag/antlr/ClagParser.interp
clag/antlr/ClagParser.py
clag/antlr/ClagParser.tokens
clag/antlr/ClagParserListener.py
clag/antlr/MakeANTLR4.ps1
clag/antlr/Makefile
clag/antlr/antlr-4.13.2-complete.jar
clag/templates/agentTemplate.py.jinja
clag/templates/envTemplate.py.jinja
clag/templates/mainTemplate.py.jinja
clag-1.0.0.dist-info/METADATA
clag-1.0.0.dist-info/WHEEL
clag-1.0.0.dist-info/entry_points.txt
clag-1.0.0.dist-info/licenses/LICENSE
clag-1.0.0.dist-info/RECORD
