Metadata-Version: 2.4
Name: clag
Version: 1.0.0
Summary: Controlled Natural Language for Agents
Project-URL: Homepage, https://github.com/laca-is/clag
Project-URL: Repository, https://github.com/laca-is/clag.git
Project-URL: Issues, https://github.com/laca-is/clag/issues
Author-email: Cainan <cainan@example.com>
License-Expression: CC-BY-NC-SA-4.0
License-File: LICENSE
Classifier: License :: Other/Proprietary License
Classifier: Operating System :: OS Independent
Classifier: Programming Language :: Python :: 3
Classifier: Programming Language :: Python :: 3.12
Classifier: Topic :: Scientific/Engineering :: Artificial Intelligence
Classifier: Topic :: Software Development :: Libraries :: Python Modules
Requires-Python: >=3.12
Requires-Dist: antlr4-python3-runtime>=4.13.1
Requires-Dist: click>=8.1.7
Requires-Dist: jinja2>=3.1.2
